project_installer/__init__.py
project_installer/constants.py
project_installer/errors.py
project_installer/installer.py
project_installer-0.1.0.dist-info/METADATA
project_installer-0.1.0.dist-info/WHEEL
project_installer-0.1.0.dist-info/licenses/LICENSE
project_installer-0.1.0.dist-info/RECORD
