Metadata-Version: 2.3
Name: project-installer
Version: 0.1.0
Summary: Download and install files from online git repositories. Currently supports only github.
Project-URL: Homepage, https://github.com/shaiksamad/project-installer
Project-URL: Repository, https://github.com/shaiksamad/project-installer.git
Project-URL: Bug Tracker, https://github.com/shaiksamad/project-installer/issues
Author-email: Shaik Abdus Samad <shaiksamad.dev@gmail.com>
License: MIT License
License-File: LICENSE
Keywords: installer,project
Classifier: Operating System :: Microsoft :: Windows
Classifier: Operating System :: Microsoft :: Windows :: Windows 7
Classifier: Operating System :: Microsoft :: Windows :: Windows 8
Classifier: Operating System :: Microsoft :: Windows :: Windows 8.1
Classifier: Operating System :: Microsoft :: Windows :: Windows 10
Classifier: Operating System :: Microsoft :: Windows :: Windows 11
Classifier: Programming Language :: Python
Classifier: Topic :: System :: Installation/Setup
Requires-Python: >=3.6
Requires-Dist: requests
